awspider
