Metadata-Version: 1.0
Name: AWSpider
Version: 0.3.1.5
Summary: Amazon Web Services web crawler
Home-page: http://github.com/wehriam/awspider/
Author: John Wehr
Author-email: johnwehr@gmail.com
License: MIT License
Keywords: AWS amazon ec2 s3 simpledb twisted spider crawler
Platform: UNKNOWN
